LICENSE
MANIFEST.in
README.md
pyproject.toml
setup.py
upload_to_pypi.py
upload_with_token.py
streamlit_ai_toolkit/__init__.py
streamlit_ai_toolkit/ai_services.py
streamlit_ai_toolkit/streamlit_ai_cli.py
streamlit_ai_toolkit/ui_components.py
streamlit_ai_toolkit.egg-info/PKG-INFO
streamlit_ai_toolkit.egg-info/SOURCES.txt
streamlit_ai_toolkit.egg-info/dependency_links.txt
streamlit_ai_toolkit.egg-info/entry_points.txt
streamlit_ai_toolkit.egg-info/requires.txt
streamlit_ai_toolkit.egg-info/top_level.txt
streamlit_ai_toolkit/templates/.env.example
streamlit_ai_toolkit/templates/.gitignore
streamlit_ai_toolkit/templates/README.md
streamlit_ai_toolkit/templates/ai_chat.py
streamlit_ai_toolkit/templates/app.py
streamlit_ai_toolkit/templates/config.example.py
streamlit_ai_toolkit/templates/deep_thinking.py
streamlit_ai_toolkit/templates/knowledge_base.py
streamlit_ai_toolkit/templates/multimodal.py
streamlit_ai_toolkit/templates/sample_knowledge.json
streamlit_ai_toolkit/templates/ui_config.py
streamlit_ai_toolkit/templates/utils.py
streamlit_ai_toolkit/templates/web_search.py