Metadata-Version: 2.1
Name: streamlit-ai-toolkit
Version: 1.2.6
Summary: A comprehensive AI toolkit for Streamlit applications with RAG and multimodal capabilities
Home-page: https://github.com/xiaozhou/streamlit-ai-toolkit
Author: Xiaozhou Team
Author-email: Xiaozhou Team <xiaozhou@example.com>
License: MIT
Project-URL: Homepage, https://github.com/xiaozhou/streamlit-ai-toolkit
Project-URL: Documentation, https://github.com/xiaozhou/streamlit-ai-toolkit#readme
Project-URL: Repository, https://github.com/xiaozhou/streamlit-ai-toolkit
Project-URL: Bug Tracker, https://github.com/xiaozhou/streamlit-ai-toolkit/issues
Keywords: streamlit,ai,rag,multimodal,nlp,computer-vision,faiss,transformers,stable-diffusion,blip
Platform: any
Classifier: Development Status :: 4 - Beta
Classifier: Intended Audience :: Developers
Classifier: License :: OSI Approved :: MIT License
Classifier: Programming Language :: Python :: 3
Classifier: Programming Language :: Python :: 3.8
Classifier: Programming Language :: Python :: 3.9
Classifier: Programming Language :: Python :: 3.10
Classifier: Programming Language :: Python :: 3.11
Classifier: Topic :: Software Development :: Libraries :: Python Modules
Classifier: Topic :: Scientific/Engineering :: Artificial Intelligence
Requires-Python: >=3.8
License-File: LICENSE
Requires-Dist: streamlit>=1.28.0
Requires-Dist: sentence-transformers>=2.2.0
Requires-Dist: faiss-cpu>=1.7.4
Requires-Dist: diffusers>=0.21.0
Requires-Dist: transformers>=4.30.0
Requires-Dist: torch>=2.0.0
Requires-Dist: Pillow>=9.0.0
Requires-Dist: numpy>=1.24.0
Requires-Dist: requests>=2.28.0
Provides-Extra: gpu
Requires-Dist: faiss-gpu>=1.7.4; extra == "gpu"
Provides-Extra: dev
Requires-Dist: pytest>=7.0.0; extra == "dev"
Requires-Dist: black>=23.0.0; extra == "dev"
Requires-Dist: flake8>=6.0.0; extra == "dev"
Requires-Dist: mypy>=1.0.0; extra == "dev"
